<?xml version="1.0" encoding="UTF-8"?>
<!DOCTYPE plist PUBLIC "-//Apple//DTD PLIST 1.0//EN" "http://www.apple.com/DTDs/PropertyList-1.0.dtd"/>

<plist version="1.0">
    <dict>
        <key>ROOT</key>
        <array>
            <dict>
                <key>id</key>
                <string>346</string>
                <key>className</key>
                <string>PTModelObjectImage</string>
                <key>Name</key>
                <dict>
                    <key>value</key>
                    <string>Untitled</string>
                </dict>
                <key>Position</key>
                <dict>
                    <key>value</key>
                    <string>{0.000,0.000}</string>
                </dict>
                <key>Scale</key>
                <dict>
                    <key>value</key>
                    <string>{1.000,1.000}</string>
                </dict>
                <key>Hidden</key>
                <dict>
                    <key>visible</key>
                    <string>0</string>
                </dict>
                <key>Locked</key>
                <dict>
                    <key>visible</key>
                    <string>0</string>
                </dict>
                <key>Stick To Edge</key>
                <dict>
                    <key>value</key>
                    <string>0</string>
                </dict>
                <key>zDepth</key>
                <string>0</string>
            </dict>
            <dict>
                <key>id</key>
                <string>447</string>
                <key>className</key>
                <string>PTModelObjectImage</string>
                <key>Name</key>
                <dict>
                    <key>value</key>
                    <string>Untitled</string>
                </dict>
                <key>Position</key>
                <dict>
                    <key>value</key>
                    <string>{0.000,0.000}</string>
                </dict>
                <key>Scale</key>
                <dict>
                    <key>value</key>
                    <string>{1.000,1.000}</string>
                </dict>
                <key>Hidden</key>
                <dict>
                    <key>visible</key>
                    <string>0</string>
                </dict>
                <key>Locked</key>
                <dict>
                    <key>visible</key>
                    <string>0</string>
                </dict>
                <key>Stick To Edge</key>
                <dict>
                    <key>value</key>
                    <string>0</string>
                </dict>
                <key>zDepth</key>
                <string>0</string>
            </dict>
            <dict>
                <key>id</key>
                <string>1453</string>
                <key>className</key>
                <string>PTModelObjectImage</string>
                <key>Name</key>
                <dict>
                    <key>value</key>
                    <string>Untitled</string>
                </dict>
                <key>Position</key>
                <dict>
                    <key>value</key>
                    <string>{0.000,0.000}</string>
                </dict>
                <key>Scale</key>
                <dict>
                    <key>value</key>
                    <string>{1.000,1.000}</string>
                </dict>
                <key>Hidden</key>
                <dict>
                    <key>visible</key>
                    <string>0</string>
                </dict>
                <key>Locked</key>
                <dict>
                    <key>visible</key>
                    <string>0</string>
                </dict>
                <key>Stick To Edge</key>
                <dict>
                    <key>value</key>
                    <string>0</string>
                </dict>
                <key>zDepth</key>
                <string>0</string>
            </dict>
            <dict>
                <key>id</key>
                <string>1598</string>
                <key>className</key>
                <string>PTModelObjectImage</string>
                <key>Name</key>
                <dict>
                    <key>value</key>
                    <string>Untitled</string>
                </dict>
                <key>Position</key>
                <dict>
                    <key>value</key>
                    <string>{0.000,0.000}</string>
                </dict>
                <key>Scale</key>
                <dict>
                    <key>value</key>
                    <string>{1.000,1.000}</string>
                </dict>
                <key>Hidden</key>
                <dict>
                    <key>visible</key>
                    <string>0</string>
                </dict>
                <key>Locked</key>
                <dict>
                    <key>visible</key>
                    <string>0</string>
                </dict>
                <key>Stick To Edge</key>
                <dict>
                    <key>value</key>
                    <string>0</string>
                </dict>
                <key>zDepth</key>
                <string>0</string>
            </dict>
            <dict>
                <key>id</key>
                <string>1607</string>
                <key>className</key>
                <string>PTModelObjectImage</string>
                <key>Name</key>
                <dict>
                    <key>value</key>
                    <string>Untitled</string>
                </dict>
                <key>Position</key>
                <dict>
                    <key>value</key>
                    <string>{0.000,0.000}</string>
                </dict>
                <key>Scale</key>
                <dict>
                    <key>value</key>
                    <string>{1.000,1.000}</string>
                </dict>
                <key>Hidden</key>
                <dict>
                    <key>visible</key>
                    <string>0</string>
                </dict>
                <key>Locked</key>
                <dict>
                    <key>visible</key>
                    <string>0</string>
                </dict>
                <key>Stick To Edge</key>
                <dict>
                    <key>value</key>
                    <string>0</string>
                </dict>
                <key>zDepth</key>
                <string>0</string>
            </dict>
            <dict>
                <key>id</key>
                <string>1699</string>
                <key>className</key>
                <string>PTModelObjectImage</string>
                <key>Name</key>
                <dict>
                    <key>value</key>
                    <string>Untitled</string>
                </dict>
                <key>Position</key>
                <dict>
                    <key>value</key>
                    <string>{0.000,0.000}</string>
                </dict>
                <key>Scale</key>
                <dict>
                    <key>value</key>
                    <string>{1.000,1.000}</string>
                </dict>
                <key>Hidden</key>
                <dict>
                    <key>visible</key>
                    <string>0</string>
                </dict>
                <key>Locked</key>
                <dict>
                    <key>visible</key>
                    <string>0</string>
                </dict>
                <key>Stick To Edge</key>
                <dict>
                    <key>value</key>
                    <string>0</string>
                </dict>
                <key>zDepth</key>
                <string>0</string>
            </dict>
            <dict>
                <key>id</key>
                <string>1843</string>
                <key>className</key>
                <string>PTModelObjectImage</string>
                <key>Name</key>
                <dict>
                    <key>value</key>
                    <string>Untitled</string>
                </dict>
                <key>Position</key>
                <dict>
                    <key>value</key>
                    <string>{568.000,320.000}</string>
                </dict>
                <key>Scale</key>
                <dict>
                    <key>value</key>
                    <string>{1.000,1.000}</string>
                </dict>
                <key>Hidden</key>
                <dict>
                    <key>visible</key>
                    <string>0</string>
                </dict>
                <key>Locked</key>
                <dict>
                    <key>visible</key>
                    <string>0</string>
                </dict>
                <key>zDepth</key>
                <string>-1</string>
            </dict>
            <dict>
                <key>id</key>
                <string>1848</string>
                <key>className</key>
                <string>PTModelObjectImage</string>
                <key>Name</key>
                <dict>
                    <key>value</key>
                    <string>Game</string>
                </dict>
                <key>Position</key>
                <dict>
                    <key>value</key>
                    <string>{568.000,416.000}</string>
                </dict>
                <key>Scale</key>
                <dict>
                    <key>value</key>
                    <string>{1.000,1.000}</string>
                </dict>
                <key>Hidden</key>
                <dict>
                    <key>visible</key>
                    <string>0</string>
                </dict>
                <key>Locked</key>
                <dict>
                    <key>visible</key>
                    <string>0</string>
                </dict>
                <key>zDepth</key>
                <string>0</string>
            </dict>
            <dict>
                <key>id</key>
                <string>1854</string>
                <key>className</key>
                <string>PTModelObjectImage</string>
                <key>Name</key>
                <dict>
                    <key>value</key>
                    <string>Untitled</string>
                </dict>
                <key>Position</key>
                <dict>
                    <key>value</key>
                    <string>{568.000,320.000}</string>
                </dict>
                <key>Scale</key>
                <dict>
                    <key>value</key>
                    <string>{1.000,1.000}</string>
                </dict>
                <key>Hidden</key>
                <dict>
                    <key>visible</key>
                    <string>0</string>
                </dict>
                <key>Locked</key>
                <dict>
                    <key>visible</key>
                    <string>0</string>
                </dict>
                <key>zDepth</key>
                <string>-1</string>
            </dict>
            <dict>
                <key>id</key>
                <string>1863</string>
                <key>className</key>
                <string>PTModelObjectImage</string>
                <key>Name</key>
                <dict>
                    <key>value</key>
                    <string>Untitled</string>
                </dict>
                <key>Position</key>
                <dict>
                    <key>value</key>
                    <string>{568.000,320.000}</string>
                </dict>
                <key>Scale</key>
                <dict>
                    <key>value</key>
                    <string>{-1136.000,-640.000}</string>
                </dict>
                <key>Hidden</key>
                <dict>
                    <key>visible</key>
                    <string>0</string>
                </dict>
                <key>Locked</key>
                <dict>
                    <key>visible</key>
                    <string>0</string>
                </dict>
                <key>zDepth</key>
                <string>-1</string>
            </dict>
            <dict>
                <key>id</key>
                <string>1866</string>
                <key>className</key>
                <string>PTModelObjectImage</string>
                <key>Name</key>
                <dict>
                    <key>value</key>
                    <string>Logo</string>
                </dict>
                <key>Position</key>
                <dict>
                    <key>value</key>
                    <string>{268.500,525.500}</string>
                </dict>
                <key>Scale</key>
                <dict>
                    <key>value</key>
                    <string>{1.000,1.000}</string>
                </dict>
                <key>Hidden</key>
                <dict>
                    <key>visible</key>
                    <string>0</string>
                </dict>
                <key>Locked</key>
                <dict>
                    <key>visible</key>
                    <string>0</string>
                </dict>
                <key>zDepth</key>
                <string>0</string>
            </dict>
            <dict>
                <key>id</key>
                <string>1876</string>
                <key>className</key>
                <string>PTModelObjectImage</string>
                <key>Name</key>
                <dict>
                    <key>value</key>
                    <string>Untitled</string>
                </dict>
                <key>Position</key>
                <dict>
                    <key>value</key>
                    <string>{568.000,320.000}</string>
                </dict>
                <key>Scale</key>
                <dict>
                    <key>value</key>
                    <string>{1.000,1.000}</string>
                </dict>
                <key>Hidden</key>
                <dict>
                    <key>visible</key>
                    <string>0</string>
                </dict>
                <key>Locked</key>
                <dict>
                    <key>visible</key>
                    <string>0</string>
                </dict>
                <key>zDepth</key>
                <string>-1</string>
            </dict>
            <dict>
                <key>id</key>
                <string>1879</string>
                <key>className</key>
                <string>PTModelObjectImage</string>
                <key>Name</key>
                <dict>
                    <key>value</key>
                    <string>Game Over</string>
                </dict>
                <key>Position</key>
                <dict>
                    <key>value</key>
                    <string>{455.500,525.500}</string>
                </dict>
                <key>Scale</key>
                <dict>
                    <key>value</key>
                    <string>{1.000,1.000}</string>
                </dict>
                <key>Hidden</key>
                <dict>
                    <key>visible</key>
                    <string>0</string>
                </dict>
                <key>Locked</key>
                <dict>
                    <key>visible</key>
                    <string>0</string>
                </dict>
                <key>zDepth</key>
                <string>0</string>
            </dict>
            <dict>
                <key>id</key>
                <string>2356</string>
                <key>className</key>
                <string>PTModelObjectImage</string>
                <key>Name</key>
                <dict>
                    <key>value</key>
                    <string>Untitled</string>
                </dict>
                <key>Position</key>
                <dict>
                    <key>value</key>
                    <string>{568.000,320.000}</string>
                </dict>
                <key>Scale</key>
                <dict>
                    <key>value</key>
                    <string>{1.000,1.000}</string>
                </dict>
                <key>Hidden</key>
                <dict>
                    <key>visible</key>
                    <string>0</string>
                </dict>
                <key>Locked</key>
                <dict>
                    <key>visible</key>
                    <string>0</string>
                </dict>
                <key>zDepth</key>
                <string>0</string>
            </dict>
            <dict>
                <key>id</key>
                <string>2441</string>
                <key>className</key>
                <string>PTModelObjectImage</string>
                <key>Name</key>
                <dict>
                    <key>value</key>
                    <string>Untitled</string>
                </dict>
                <key>Position</key>
                <dict>
                    <key>value</key>
                    <string>{568.000,320.000}</string>
                </dict>
                <key>Scale</key>
                <dict>
                    <key>value</key>
                    <string>{1.000,1.000}</string>
                </dict>
                <key>Hidden</key>
                <dict>
                    <key>visible</key>
                    <string>0</string>
                </dict>
                <key>Locked</key>
                <dict>
                    <key>visible</key>
                    <string>0</string>
                </dict>
                <key>zDepth</key>
                <string>0</string>
            </dict>
            <dict>
                <key>id</key>
                <string>3253</string>
                <key>className</key>
                <string>PTModelObjectImage</string>
                <key>Name</key>
                <dict>
                    <key>value</key>
                    <string>KeyHole</string>
                </dict>
                <key>Position</key>
                <dict>
                    <key>value</key>
                    <string>{0.000,0.000}</string>
                </dict>
                <key>Scale</key>
                <dict>
                    <key>value</key>
                    <string>{1.000,1.000}</string>
                </dict>
                <key>Hidden</key>
                <dict>
                    <key>visible</key>
                    <string>0</string>
                </dict>
                <key>Locked</key>
                <dict>
                    <key>visible</key>
                    <string>0</string>
                </dict>
                <key>Opacity</key>
                <dict>
                    <key>value</key>
                    <string>0.000000</string>
                </dict>
                <key>Stick To Edge</key>
                <dict>
                    <key>value</key>
                    <string>0</string>
                </dict>
                <key>zDepth</key>
                <string>0</string>
            </dict>
            <dict>
                <key>id</key>
                <string>3352</string>
                <key>className</key>
                <string>PTModelObjectImage</string>
                <key>Name</key>
                <dict>
                    <key>value</key>
                    <string>1Coin4</string>
                </dict>
                <key>Position</key>
                <dict>
                    <key>value</key>
                    <string>{0.000,0.000}</string>
                </dict>
                <key>Scale</key>
                <dict>
                    <key>value</key>
                    <string>{1.000,1.000}</string>
                </dict>
                <key>Hidden</key>
                <dict>
                    <key>visible</key>
                    <string>0</string>
                </dict>
                <key>Locked</key>
                <dict>
                    <key>visible</key>
                    <string>0</string>
                </dict>
                <key>Stick To Edge</key>
                <dict>
                    <key>value</key>
                    <string>0</string>
                </dict>
                <key>zDepth</key>
                <string>0</string>
            </dict>
            <dict>
                <key>id</key>
                <string>3367</string>
                <key>className</key>
                <string>PTModelObjectImage</string>
                <key>Name</key>
                <dict>
                    <key>value</key>
                    <string>2Coin4</string>
                </dict>
                <key>Position</key>
                <dict>
                    <key>value</key>
                    <string>{0.000,0.000}</string>
                </dict>
                <key>Scale</key>
                <dict>
                    <key>value</key>
                    <string>{1.000,1.000}</string>
                </dict>
                <key>Hidden</key>
                <dict>
                    <key>visible</key>
                    <string>0</string>
                </dict>
                <key>Locked</key>
                <dict>
                    <key>visible</key>
                    <string>0</string>
                </dict>
                <key>Stick To Edge</key>
                <dict>
                    <key>value</key>
                    <string>0</string>
                </dict>
                <key>zDepth</key>
                <string>0</string>
            </dict>
            <dict>
                <key>id</key>
                <string>3378</string>
                <key>className</key>
                <string>PTModelObjectImage</string>
                <key>Name</key>
                <dict>
                    <key>value</key>
                    <string>1CoinPurple</string>
                </dict>
                <key>Position</key>
                <dict>
                    <key>value</key>
                    <string>{0.000,0.000}</string>
                </dict>
                <key>Scale</key>
                <dict>
                    <key>value</key>
                    <string>{1.000,1.000}</string>
                </dict>
                <key>Hidden</key>
                <dict>
                    <key>visible</key>
                    <string>0</string>
                </dict>
                <key>Locked</key>
                <dict>
                    <key>visible</key>
                    <string>0</string>
                </dict>
                <key>Stick To Edge</key>
                <dict>
                    <key>value</key>
                    <string>0</string>
                </dict>
                <key>zDepth</key>
                <string>0</string>
            </dict>
            <dict>
                <key>id</key>
                <string>3388</string>
                <key>className</key>
                <string>PTModelObjectImage</string>
                <key>Name</key>
                <dict>
                    <key>value</key>
                    <string>3CoinPurple</string>
                </dict>
                <key>Position</key>
                <dict>
                    <key>value</key>
                    <string>{0.000,0.000}</string>
                </dict>
                <key>Scale</key>
                <dict>
                    <key>value</key>
                    <string>{1.000,1.000}</string>
                </dict>
                <key>Hidden</key>
                <dict>
                    <key>visible</key>
                    <string>0</string>
                </dict>
                <key>Locked</key>
                <dict>
                    <key>visible</key>
                    <string>0</string>
                </dict>
                <key>Stick To Edge</key>
                <dict>
                    <key>value</key>
                    <string>0</string>
                </dict>
                <key>zDepth</key>
                <string>0</string>
            </dict>
            <dict>
                <key>id</key>
                <string>4340</string>
                <key>className</key>
                <string>PTModelObjectImage</string>
                <key>Name</key>
                <dict>
                    <key>value</key>
                    <string>Bikes</string>
                </dict>
                <key>Position</key>
                <dict>
                    <key>value</key>
                    <string>{0.000,0.000}</string>
                </dict>
                <key>Scale</key>
                <dict>
                    <key>value</key>
                    <string>{1.000,1.000}</string>
                </dict>
                <key>Hidden</key>
                <dict>
                    <key>visible</key>
                    <string>0</string>
                </dict>
                <key>Locked</key>
                <dict>
                    <key>visible</key>
                    <string>0</string>
                </dict>
                <key>Stick To Edge</key>
                <dict>
                    <key>value</key>
                    <string>0</string>
                </dict>
                <key>zDepth</key>
                <string>0</string>
            </dict>
            <dict>
                <key>id</key>
                <string>4526</string>
                <key>className</key>
                <string>PTModelObjectImage</string>
                <key>Name</key>
                <dict>
                    <key>value</key>
                    <string>Untitled</string>
                </dict>
                <key>Position</key>
                <dict>
                    <key>value</key>
                    <string>{568.000,320.000}</string>
                </dict>
                <key>Scale</key>
                <dict>
                    <key>value</key>
                    <string>{1.000,1.000}</string>
                </dict>
                <key>Hidden</key>
                <dict>
                    <key>visible</key>
                    <string>0</string>
                </dict>
                <key>Locked</key>
                <dict>
                    <key>visible</key>
                    <string>0</string>
                </dict>
                <key>zDepth</key>
                <string>0</string>
            </dict>
            <dict>
                <key>id</key>
                <string>4926</string>
                <key>className</key>
                <string>PTModelObjectImage</string>
                <key>Name</key>
                <dict>
                    <key>value</key>
                    <string>Untitled</string>
                </dict>
                <key>Position</key>
                <dict>
                    <key>value</key>
                    <string>{568.000,320.000}</string>
                </dict>
                <key>Scale</key>
                <dict>
                    <key>value</key>
                    <string>{1.000,1.000}</string>
                </dict>
                <key>Hidden</key>
                <dict>
                    <key>visible</key>
                    <string>0</string>
                </dict>
                <key>Locked</key>
                <dict>
                    <key>visible</key>
                    <string>0</string>
                </dict>
                <key>zDepth</key>
                <string>0</string>
            </dict>
            <dict>
                <key>id</key>
                <string>5328</string>
                <key>className</key>
                <string>PTModelObjectImage</string>
                <key>Name</key>
                <dict>
                    <key>value</key>
                    <string>WhiteCircle copy</string>
                </dict>
                <key>Position</key>
                <dict>
                    <key>value</key>
                    <string>{0.000,0.000}</string>
                </dict>
                <key>Scale</key>
                <dict>
                    <key>value</key>
                    <string>{1.000,1.000}</string>
                </dict>
                <key>Hidden</key>
                <dict>
                    <key>visible</key>
                    <string>0</string>
                </dict>
                <key>Locked</key>
                <dict>
                    <key>visible</key>
                    <string>0</string>
                </dict>
                <key>zDepth</key>
                <string>0</string>
            </dict>
            <dict>
                <key>id</key>
                <string>5521</string>
                <key>className</key>
                <string>PTModelObjectImage</string>
                <key>Name</key>
                <dict>
                    <key>value</key>
                    <string>Untitled</string>
                </dict>
                <key>Position</key>
                <dict>
                    <key>value</key>
                    <string>{568.000,320.000}</string>
                </dict>
                <key>Scale</key>
                <dict>
                    <key>value</key>
                    <string>{1.000,1.000}</string>
                </dict>
                <key>Hidden</key>
                <dict>
                    <key>visible</key>
                    <string>0</string>
                </dict>
                <key>Locked</key>
                <dict>
                    <key>visible</key>
                    <string>0</string>
                </dict>
                <key>zDepth</key>
                <string>0</string>
            </dict>
            <dict>
                <key>id</key>
                <string>5705</string>
                <key>className</key>
                <string>PTModelObjectImage</string>
                <key>Name</key>
                <dict>
                    <key>value</key>
                    <string>WhiteCircle copy</string>
                </dict>
                <key>Position</key>
                <dict>
                    <key>value</key>
                    <string>{0.000,0.000}</string>
                </dict>
                <key>Scale</key>
                <dict>
                    <key>value</key>
                    <string>{1.000,1.000}</string>
                </dict>
                <key>Hidden</key>
                <dict>
                    <key>visible</key>
                    <string>0</string>
                </dict>
                <key>Locked</key>
                <dict>
                    <key>visible</key>
                    <string>0</string>
                </dict>
                <key>Stick To Edge</key>
                <dict>
                    <key>value</key>
                    <string>0</string>
                </dict>
                <key>zDepth</key>
                <string>0</string>
            </dict>
            <dict>
                <key>id</key>
                <string>5722</string>
                <key>className</key>
                <string>PTModelObjectImage</string>
                <key>Name</key>
                <dict>
                    <key>value</key>
                    <string>Jump</string>
                </dict>
                <key>Position</key>
                <dict>
                    <key>value</key>
                    <string>{0.000,0.000}</string>
                </dict>
                <key>Scale</key>
                <dict>
                    <key>value</key>
                    <string>{1.000,1.000}</string>
                </dict>
                <key>Hidden</key>
                <dict>
                    <key>visible</key>
                    <string>0</string>
                </dict>
                <key>Locked</key>
                <dict>
                    <key>visible</key>
                    <string>0</string>
                </dict>
                <key>Stick To Edge</key>
                <dict>
                    <key>value</key>
                    <string>0</string>
                </dict>
                <key>zDepth</key>
                <string>0</string>
            </dict>
            <dict>
                <key>id</key>
                <string>5753</string>
                <key>className</key>
                <string>PTModelObjectImage</string>
                <key>Name</key>
                <dict>
                    <key>value</key>
                    <string>TapToJump</string>
                </dict>
                <key>Position</key>
                <dict>
                    <key>value</key>
                    <string>{0.000,50.000}</string>
                </dict>
                <key>Scale</key>
                <dict>
                    <key>value</key>
                    <string>{0.500,0.500}</string>
                </dict>
                <key>Hidden</key>
                <dict>
                    <key>visible</key>
                    <string>0</string>
                </dict>
                <key>Locked</key>
                <dict>
                    <key>visible</key>
                    <string>0</string>
                </dict>
                <key>Stick To Edge</key>
                <dict>
                    <key>value</key>
                    <string>0</string>
                </dict>
                <key>zDepth</key>
                <string>0</string>
            </dict>
            <dict>
                <key>id</key>
                <string>5877</string>
                <key>className</key>
                <string>PTModelObjectImage</string>
                <key>Name</key>
                <dict>
                    <key>value</key>
                    <string>WhiteCircle copy</string>
                </dict>
                <key>Position</key>
                <dict>
                    <key>value</key>
                    <string>{0.000,0.000}</string>
                </dict>
                <key>Scale</key>
                <dict>
                    <key>value</key>
                    <string>{1.000,1.000}</string>
                </dict>
                <key>Hidden</key>
                <dict>
                    <key>visible</key>
                    <string>0</string>
                </dict>
                <key>Locked</key>
                <dict>
                    <key>visible</key>
                    <string>0</string>
                </dict>
                <key>Stick To Edge</key>
                <dict>
                    <key>value</key>
                    <string>0</string>
                </dict>
                <key>zDepth</key>
                <string>0</string>
            </dict>
            <dict>
                <key>id</key>
                <string>5890</string>
                <key>className</key>
                <string>PTModelObjectImage</string>
                <key>Name</key>
                <dict>
                    <key>value</key>
                    <string>HoldToRotate</string>
                </dict>
                <key>Position</key>
                <dict>
                    <key>value</key>
                    <string>{0.000,50.000}</string>
                </dict>
                <key>Scale</key>
                <dict>
                    <key>value</key>
                    <string>{0.500,0.500}</string>
                </dict>
                <key>Hidden</key>
                <dict>
                    <key>visible</key>
                    <string>0</string>
                </dict>
                <key>Locked</key>
                <dict>
                    <key>visible</key>
                    <string>0</string>
                </dict>
                <key>Stick To Edge</key>
                <dict>
                    <key>value</key>
                    <string>0</string>
                </dict>
                <key>zDepth</key>
                <string>0</string>
            </dict>
        </array>
    </dict>
</plist>
