<?xml version="1.0" encoding="UTF-8"?>
<!DOCTYPE plist PUBLIC "-//Apple//DTD PLIST 1.0//EN" "http://www.apple.com/DTDs/PropertyList-1.0.dtd"/>

<plist version="1.0">
    <dict>
        <key>ROOT</key>
        <array>
            <dict>
                <key>id</key>
                <string>100</string>
                <key>children</key>
                <array>
                    <string>2413</string>
                </array>
            </dict>
            <dict>
                <key>id</key>
                <string>188</string>
                <key>children</key>
                <array>
                    <string>2414</string>
                </array>
            </dict>
            <dict>
                <key>id</key>
                <string>194</string>
                <key>children</key>
                <array>
                    <string>2415</string>
                </array>
            </dict>
            <dict>
                <key>id</key>
                <string>200</string>
                <key>children</key>
                <array>
                    <string>2416</string>
                </array>
            </dict>
        </array>
    </dict>
</plist>
